LICENSE
MANIFEST.in
README.md
setup.py
_/__init__.py
_/application.py
_/auth.py
_/components.py
_/handlers.py
_/settings.py
_/utils.py
_/version.py
_/websockets.py
_/__pycache__/__init__.cpython-312.pyc
_/__pycache__/application.cpython-312.pyc
_/__pycache__/auth.cpython-312.pyc
_/__pycache__/components.cpython-312.pyc
_/__pycache__/handlers.cpython-312.pyc
_/__pycache__/settings.cpython-312.pyc
_/__pycache__/utils.cpython-312.pyc
_/__pycache__/version.cpython-312.pyc
_/caches/__init__.py
_/caches/dbcache.py
_/caches/memory.py
_/caches/redis.py
_/databases/__init__.py
_/databases/postgres.py
_/databases/sqlite.py
_/logins/__init__.py
_/logins/dblogin.py
_/logins/facebook.py
_/logins/gitlab.py
_/logins/google.py
_/logins/htpasswd.py
_/logins/oauth2.py
_/logins/slap.py
_/records/Protobuf.proto
_/records/Protobuf_pb2.py
_/records/__init__.py
_/records/data.py
_/records/protobuf.py
_/records/__pycache__/Protobuf_pb2.cpython-312.pyc
_/records/__pycache__/__init__.cpython-312.pyc
_/records/__pycache__/protobuf.cpython-312.pyc
_/supports/__init__.py
_/supports/nginx/__init__.py
_/supports/nginx/nginx.conf
_/supports/systemd/__init__.py
_/supports/systemd/systemd.service
underscorepy.egg-info/PKG-INFO
underscorepy.egg-info/SOURCES.txt
underscorepy.egg-info/dependency_links.txt
underscorepy.egg-info/not-zip-safe
underscorepy.egg-info/requires.txt
underscorepy.egg-info/top_level.txt