Metadata-Version: 2.1
Name: underscorepy
Version: 0.6.4
Summary: _.py library
Home-page: https://shaw.cx/_.py
Author: Matthew Shaw
Author-email: mshaw.cx@gmail.com
License: MIT
Classifier: Development Status :: 3 - Alpha
Classifier: Intended Audience :: Developers
Classifier: License :: OSI Approved :: MIT License
Classifier: Topic :: Software Development :: Libraries
Classifier: Programming Language :: Python :: 3.7
License-File: LICENSE
Requires-Dist: tornado
